setup.py
src/futuregrid_passwdstack/__init__.py
src/futuregrid_passwdstack.egg-info/PKG-INFO
src/futuregrid_passwdstack.egg-info/SOURCES.txt
src/futuregrid_passwdstack.egg-info/dependency_links.txt
src/futuregrid_passwdstack.egg-info/not-zip-safe
src/futuregrid_passwdstack.egg-info/requires.txt
src/futuregrid_passwdstack.egg-info/top_level.txt
src/futuregrid_passwdstack/passwdstack/PasswdStack.py
src/futuregrid_passwdstack/passwdstack/PasswdStackClientConf.py
src/futuregrid_passwdstack/passwdstack/PasswdStackServer.py
src/futuregrid_passwdstack/passwdstack/PasswdStackServerConf.py
src/futuregrid_passwdstack/passwdstack/__init__.py
src/futuregrid_passwdstack/passwdstack/fg-passwdstack
src/futuregrid_passwdstack/utils/FGAuth.py
src/futuregrid_passwdstack/utils/FGTypes.py
src/futuregrid_passwdstack/utils/__init__.py
src/futuregrid_passwdstack/utils/fgLog.py