Metadata-Version: 1.0
Name: futuregrid-passwdstack
Version: 0.1
Summary: Password Stack is a simple tool that allows normal users to reset their own password in the OpenStack Dashboard
Home-page: http://futuregrid.github.com/passwdstack/index.html
Author: Javier Diaz, Koji Tanaka, Fugang Wang, Gregor von Laszewski
Author-email: javier.diazmontes@gmail.com
License: Apache Software License
Keywords: Cloud,Grid,HPC
Platform: UNKNOWN
Classifier: Development Status :: 4 - Beta
Classifier: Intended Audience :: Developers
Classifier: Intended Audience :: System Administrators
Classifier: License :: OSI Approved :: Apache Software License
Classifier: Operating System :: OS Independent
Classifier: Programming Language :: Python
Classifier: Topic :: Software Development :: Libraries :: Python Modules
Classifier: Topic :: Scientific/Engineering
Classifier: Topic :: System :: Distributed Computing
